slav/__init__.py
slav/components/__init__.py
slav/components/button.py
slav/components/checkbox.py
slav/components/dialog.py
slav/components/input.py
slav/components/list.py
slav/components/menu.py
slav/components/progress.py
slav/components/text.py
slav/core/__init__.py
slav/core/component.py
slav/core/event.py
slav/core/screen.py
slav/examples/__init__.py
slav/examples/demo.py
slav/examples/simple.py
slav/layout/__init__.py
slav/layout/box.py
slav/layout/grid.py
slav/utils/__init__.py
slav/utils/colors.py
slav/utils/keys.py
slav/utils/terminal.py
slav-1.0.1.dist-info/licenses/LICENSE
tests/__init__.py
tests/test_components.py
tests/test_core.py
tests/test_layout.py
slav-1.0.1.dist-info/METADATA
slav-1.0.1.dist-info/WHEEL
slav-1.0.1.dist-info/entry_points.txt
slav-1.0.1.dist-info/top_level.txt
slav-1.0.1.dist-info/RECORD
